{
  "format-version": 0,
  "modules": [
    "mod-action",
    "mod-api",
    "mod-appservice",
    "mod-auth",
    "mod-authz",
    "mod-db",
    "mod-devscript",
    "mod-domainservice",
    "mod-event",
    "mod-handler",
    "mod-lib",
    "mod-mcp",
    "mod-model",
    "mod-proxy",
    "mod-repo",
    "mod-ui",
    "mod-usecase",
    "mod-webhook"
  ],
  "paths": {
    "mod-action": [
      "src/app/actions/"
    ],
    "mod-api": [
      "src/app/api/"
    ],
    "mod-appservice": [
      "src/application/services/"
    ],
    "mod-auth": [
      "src/infrastructure/auth.ts",
      "src/infrastructure/apiTokenResolver.ts"
    ],
    "mod-authz": [
      "src/domain/authorization.ts"
    ],
    "mod-db": [
      "src/infrastructure/schema.ts",
      "src/infrastructure/db.ts"
    ],
    "mod-devscript": [
      "src/infrastructure/seed.ts",
      "src/infrastructure/reset.ts"
    ],
    "mod-domainservice": [
      "src/domain/services/"
    ],
    "mod-event": [
      "src/domain/events/"
    ],
    "mod-handler": [
      "src/infrastructure/handlers/",
      "src/instrumentation.ts"
    ],
    "mod-lib": [
      "src/lib/"
    ],
    "mod-mcp": [
      "src/app/api/mcp/"
    ],
    "mod-model": [
      "src/domain/models/"
    ],
    "mod-proxy": [
      "src/proxy.ts"
    ],
    "mod-repo": [
      "src/infrastructure/repositories/"
    ],
    "mod-ui": [
      "src/app/(dashboard)/",
      "src/app/(platform)/",
      "src/app/(auth)/",
      "src/app/components/",
      "src/app/layout.tsx",
      "src/app/page.tsx"
    ],
    "mod-usecase": [
      "src/application/usecases/"
    ],
    "mod-webhook": [
      "src/infrastructure/webhookDelivery.ts",
      "src/infrastructure/rateLimit.ts"
    ]
  },
  "allowed": [
    [
      "mod-action",
      "mod-appservice"
    ],
    [
      "mod-action",
      "mod-auth"
    ],
    [
      "mod-action",
      "mod-authz"
    ],
    [
      "mod-action",
      "mod-domainservice"
    ],
    [
      "mod-action",
      "mod-model"
    ],
    [
      "mod-action",
      "mod-repo"
    ],
    [
      "mod-action",
      "mod-usecase"
    ],
    [
      "mod-action",
      "mod-webhook"
    ],
    [
      "mod-api",
      "mod-auth"
    ],
    [
      "mod-api",
      "mod-authz"
    ],
    [
      "mod-api",
      "mod-repo"
    ],
    [
      "mod-api",
      "mod-usecase"
    ],
    [
      "mod-appservice",
      "mod-db"
    ],
    [
      "mod-appservice",
      "mod-model"
    ],
    [
      "mod-appservice",
      "mod-repo"
    ],
    [
      "mod-auth",
      "mod-db"
    ],
    [
      "mod-auth",
      "mod-model"
    ],
    [
      "mod-auth",
      "mod-repo"
    ],
    [
      "mod-authz",
      "mod-model"
    ],
    [
      "mod-devscript",
      "mod-db"
    ],
    [
      "mod-domainservice",
      "mod-model"
    ],
    [
      "mod-event",
      "mod-model"
    ],
    [
      "mod-handler",
      "mod-appservice"
    ],
    [
      "mod-handler",
      "mod-db"
    ],
    [
      "mod-handler",
      "mod-event"
    ],
    [
      "mod-handler",
      "mod-model"
    ],
    [
      "mod-handler",
      "mod-repo"
    ],
    [
      "mod-handler",
      "mod-usecase"
    ],
    [
      "mod-handler",
      "mod-webhook"
    ],
    [
      "mod-lib",
      "mod-model"
    ],
    [
      "mod-mcp",
      "mod-appservice"
    ],
    [
      "mod-mcp",
      "mod-auth"
    ],
    [
      "mod-mcp",
      "mod-authz"
    ],
    [
      "mod-mcp",
      "mod-lib"
    ],
    [
      "mod-mcp",
      "mod-model"
    ],
    [
      "mod-mcp",
      "mod-repo"
    ],
    [
      "mod-mcp",
      "mod-usecase"
    ],
    [
      "mod-mcp",
      "mod-webhook"
    ],
    [
      "mod-proxy",
      "mod-auth"
    ],
    [
      "mod-repo",
      "mod-db"
    ],
    [
      "mod-repo",
      "mod-model"
    ],
    [
      "mod-ui",
      "mod-action"
    ],
    [
      "mod-ui",
      "mod-auth"
    ],
    [
      "mod-ui",
      "mod-authz"
    ],
    [
      "mod-ui",
      "mod-domainservice"
    ],
    [
      "mod-ui",
      "mod-lib"
    ],
    [
      "mod-ui",
      "mod-model"
    ],
    [
      "mod-ui",
      "mod-repo"
    ],
    [
      "mod-ui",
      "mod-usecase"
    ],
    [
      "mod-usecase",
      "mod-appservice"
    ],
    [
      "mod-usecase",
      "mod-db"
    ],
    [
      "mod-usecase",
      "mod-domainservice"
    ],
    [
      "mod-usecase",
      "mod-event"
    ],
    [
      "mod-usecase",
      "mod-lib"
    ],
    [
      "mod-usecase",
      "mod-model"
    ],
    [
      "mod-usecase",
      "mod-repo"
    ],
    [
      "mod-webhook",
      "mod-db"
    ],
    [
      "mod-webhook",
      "mod-model"
    ]
  ]
}
